examples/simple.py
examples/with_db_model.py
tracesql/__init__.py
tracesql/client.py
tracesql/functions.py
tracesql/model.py
tracesql/py.typed
tracesql/version.py
tracesql-0.1.10.dist-info/LICENSE
tracesql-0.1.10.dist-info/METADATA
tracesql-0.1.10.dist-info/WHEEL
tracesql-0.1.10.dist-info/top_level.txt
tracesql-0.1.10.dist-info/RECORD
